djvurn_rbac/__init__.py
djvurn_rbac/api/__init__.py
djvurn_rbac/api/permissions.py
djvurn_rbac/api/serializers.py
djvurn_rbac/api/views.py
djvurn_rbac/apps.py
djvurn_rbac/models.py
djvurn_rbac-0.1.0.dist-info/METADATA
djvurn_rbac-0.1.0.dist-info/WHEEL
djvurn_rbac-0.1.0.dist-info/licenses/LICENSE
djvurn_rbac-0.1.0.dist-info/RECORD
