Metadata-Version: 2.4
Name: djvurn-rbac
Version: 0.1.0
Summary: RBAC with teams and DRF integration
License: MIT
License-File: LICENSE
Keywords: django,rest-framework,vue,typescript,django-guardian
Author: Gojjo Tech
Author-email: dev@gojjo.tech
Requires-Python: >=3.11,<4.0
Classifier: Development Status :: 3 - Alpha
Classifier: Framework :: Django
Classifier: Framework :: Django :: 5.0
Classifier: Intended Audience :: Developers
Classifier: License :: OSI Approved :: MIT License
Classifier: Operating System :: OS Independent
Classifier: Programming Language :: Python
Classifier: Programming Language :: Python :: 3
Classifier: Programming Language :: Python :: 3.11
Classifier: Programming Language :: Python :: 3.12
Classifier: Programming Language :: Python :: 3.13
Classifier: Programming Language :: Python :: 3.14
Classifier: Topic :: Software Development :: Libraries :: Python Modules
Requires-Dist: django (>=5.0,<6.0)
Requires-Dist: django-guardian (>=3.2.0,<4.0.0)
Requires-Dist: djangorestframework (>=3.14,<4.0)
Requires-Dist: djangorestframework-simplejwt (>=5.3.0,<6.0.0)
Project-URL: Documentation, https://djvurn-rbac.readthedocs.io
Project-URL: Homepage, https://github.com/hmesfin/djvurn-packages
Project-URL: Repository, https://github.com/hmesfin/djvurn-packages
